netbox4_interface_sync/__init__.py
netbox4_interface_sync/forms.py
netbox4_interface_sync/template_content.py
netbox4_interface_sync/urls.py
netbox4_interface_sync/utils.py
netbox4_interface_sync/views.py
netbox4_interface_sync/templates/netbox4_interface_sync/compare_interfaces_button.html
netbox4_interface_sync/templates/netbox4_interface_sync/interface_comparison.html
netbox4_interface_sync/templates/netbox4_interface_sync/number_of_interfaces_panel.html
netbox4_interface_sync-4.0.2.dist-info/LICENSE
netbox4_interface_sync-4.0.2.dist-info/METADATA
netbox4_interface_sync-4.0.2.dist-info/WHEEL
netbox4_interface_sync-4.0.2.dist-info/top_level.txt
netbox4_interface_sync-4.0.2.dist-info/RECORD
