Metadata-Version: 2.1
Name: netbox4_interface_sync
Version: 4.0.2
Summary: Syncing Device Interfaces with the Interfaces from Device Type for NetBox 4
Author-email: Keith Knowles <mkknowles@outlook.com>
Project-URL: Homepage, https://github.com/NetTech2001/netbox4-interface-sync
Project-URL: Issues, https://github.com/NetTech2001/netbox4-interface-sync/issues
Classifier: Programming Language :: Python :: 3
Classifier: License :: OSI Approved :: GNU General Public License v3 (GPLv3)
Classifier: Operating System :: OS Independent
Requires-Python: >=3.11
License-File: LICENSE
